discodo/__init__.py
discodo/__main__.py
discodo/config.py
discodo/connector.py
discodo/enums.py
discodo/errors.py
discodo/events.py
discodo/gateway.py
discodo/manager.py
discodo/planner.py
discodo/player.py
discodo/voice_client.py
discodo/client/DPYClient.py
discodo/client/__init__.py
discodo/client/gateway.py
discodo/client/http.py
discodo/client/models.py
discodo/client/node.py
discodo/client/voice_client.py
discodo/extractor/__init__.py
discodo/extractor/local.py
discodo/extractor/youtube_dl.py
discodo/extractor/resolver/__init__.py
discodo/extractor/resolver/melon.py
discodo/extractor/resolver/spotify.py
discodo/extractor/resolver/vibe.py
discodo/extractor/youtube/__init__.py
discodo/extractor/youtube/mix.py
discodo/extractor/youtube/playlist.py
discodo/extractor/youtube/search.py
discodo/extractor/youtube/subtitle.py
discodo/natives/AudioFifo.py
discodo/natives/AudioFilter.py
discodo/natives/__init__.py
discodo/natives/encrypt.py
discodo/natives/opus.py
discodo/natives/bin/libopus-0.x64.dll
discodo/natives/bin/libopus-0.x86.dll
discodo/server/__init__.py
discodo/server/payloads.py
discodo/server/planner.py
discodo/server/restful.py
discodo/server/server.py
discodo/server/websocket.py
discodo/source/AudioData.py
discodo/source/AudioSource.py
discodo/source/PyAVSource.py
discodo/source/SubtitleSource.py
discodo/source/__init__.py
discodo/source/abc.py
discodo/utils/__init__.py
discodo/utils/callbackList.py
discodo/utils/eventDispatcher.py
discodo/utils/status.py
discodo/utils/tcp.py
discodo/utils/threadLock.py
test/__init__.py
test/test_resolver.py
test/test_subtitle.py
test/test_youtube.py
discodo-3.0.5.dist-info/LICENSE
discodo-3.0.5.dist-info/METADATA
discodo-3.0.5.dist-info/WHEEL
discodo-3.0.5.dist-info/top_level.txt
discodo-3.0.5.dist-info/RECORD
