Metadata-Version: 2.1
Name: discodo
Version: 3.0.5
Summary: Audio Player for Discord
Home-page: https://github.com/kijk2869/discodo
Author: kijk2869
License: MIT
Project-URL: Source, https://github.com/kijk2869/discodo
Project-URL: Tracker, https://github.com/kijk2869/discodo/issues
Platform: UNKNOWN
Classifier: Environment :: Console
Classifier: Programming Language :: Python :: 3.7
Classifier: Programming Language :: Python :: 3.8
Classifier: Programming Language :: Python :: Implementation
Classifier: Programming Language :: Python :: Implementation :: CPython
Requires-Python: >=3.7
Requires-Dist: aiohttp[speedups] (<3.8.0,>=3.6.0)
Requires-Dist: websockets (==9.1)
Requires-Dist: asyncspotify (==0.12.1)
Requires-Dist: av (==8.0.3)
Requires-Dist: PyNaCl (==1.4.0)
Requires-Dist: youtube-dl (>=2021.4.7)
Requires-Dist: youtube-related (==1.0.2)
Requires-Dist: bs4 (==0.0.1)
Requires-Dist: lxml (==4.6.3)
Requires-Dist: defusedxml (==0.7.1)
Requires-Dist: markdownify (==0.9.2)
Requires-Dist: rich (==10.6.0)
Requires-Dist: sanic (==21.6.2)
Requires-Dist: psutil (==5.8.0)
Requires-Dist: uvloop (>=0.5.3) ; sys_platform != "win32" and implementation_name == "cpython"
